omgpy/__init__.py
omgpy/bitcoin.py
omgpy/omg.py
omgpy/templates/__init__.py
omgpy/templates/canary.tpl
omgpy/templates/mirrors.tpl
omgpy/templates/related.tpl
omgpy-0.0.1.dist-info/LICENSE.md
omgpy-0.0.1.dist-info/METADATA
omgpy-0.0.1.dist-info/WHEEL
omgpy-0.0.1.dist-info/top_level.txt
omgpy-0.0.1.dist-info/RECORD
