Metadata-Version: 2.1
Name: omgpy
Version: 0.0.1
Summary: Python helper package for implementing Onion Mirror Guidelines (OMG)
Home-page: https://code.samourai.io/walletguy/omg-py
Author: WalletGuy
Author-email: wg@streetside.dev
License: UNKNOWN
Platform: UNKNOWN
Classifier: Programming Language :: Python :: 3
Classifier: License :: Public Domain
Classifier: Operating System :: OS Independent
Requires-Python: >=3.6
